ciscodnacapphosting/__init__.py
ciscodnacapphosting/cli.py
ciscodnacapphosting/dockerctl.py
ciscodnacapphosting-0.1.1.dist-info/LICENSE.txt
ciscodnacapphosting-0.1.1.dist-info/METADATA
ciscodnacapphosting-0.1.1.dist-info/WHEEL
ciscodnacapphosting-0.1.1.dist-info/entry_points.txt
ciscodnacapphosting-0.1.1.dist-info/top_level.txt
ciscodnacapphosting-0.1.1.dist-info/RECORD
