Metadata-Version: 2.1
Name: ciscodnacapphosting
Version: 0.1.1
Summary: Cisco DNA Center App Hosting SDK
Home-page: https://github.com/robertcsapo/cisco-dnac-app-hosting-import-docker-images/
Author: Robert Csapo
Author-email: rcsapo@cisco.com
License: Cisco Sample Code License, Version 1.1
Platform: UNKNOWN
Classifier: Programming Language :: Python :: 3.8
Classifier: Operating System :: OS Independent
Classifier: Topic :: Software Development :: Build Tools
Classifier: License :: Other/Proprietary License
Requires-Python: >=3.8
Requires-Dist: PyYAML (==5.4.1)
Requires-Dist: certifi (==2020.11.8)
Requires-Dist: chardet (==3.0.4)
Requires-Dist: click (==7.1.2)
Requires-Dist: docker (==4.3.1)
Requires-Dist: idna (==2.10)
Requires-Dist: requests-toolbelt (==0.9.1)
Requires-Dist: requests (==2.24.0)
Requires-Dist: six (==1.15.0)
Requires-Dist: urllib3 (==1.25.11)
Requires-Dist: websocket-client (==0.57.0)
Requires-Dist: xmltodict (==0.12.0)
